amazon_sns_mobile_push_notification/__init__.py
amazon_sns_mobile_push_notification/admin.py
amazon_sns_mobile_push_notification/apps.py
amazon_sns_mobile_push_notification/client.py
amazon_sns_mobile_push_notification/models.py
amazon_sns_mobile_push_notification/tasks.py
amazon_sns_mobile_push_notification/tests.py
django_amazon_sns_mobile_push_notification-0.1.1.dist-info/LICENSE
django_amazon_sns_mobile_push_notification-0.1.1.dist-info/METADATA
django_amazon_sns_mobile_push_notification-0.1.1.dist-info/WHEEL
django_amazon_sns_mobile_push_notification-0.1.1.dist-info/top_level.txt
django_amazon_sns_mobile_push_notification-0.1.1.dist-info/RECORD
