Metadata-Version: 2.1
Name: django-amazon-sns-mobile-push-notification
Version: 0.1.1
Summary: Send mobile push notification to IOS and android devices using Amazon SNS.
Home-page: https://github.com/ErnestoFGonzalez/django-amazon-sns-mobile-push-notification
Author: Ernesto F. González
Author-email: ernesto@hunchat.com
License: MIT License
Platform: UNKNOWN
Classifier: Environment :: Web Environment
Classifier: Framework :: Django
Classifier: Intended Audience :: Developers
Classifier: License :: OSI Approved :: MIT License
Classifier: Operating System :: OS Independent
Classifier: Programming Language :: Python
Classifier: Programming Language :: Python :: 3
Classifier: Topic :: Internet :: WWW/HTTP
Classifier: Topic :: Internet :: WWW/HTTP :: Dynamic Content
License-File: LICENSE
Requires-Dist: boto3 (>=1)
